docx_json_replacer/__init__.py
docx_json_replacer/cli.py
docx_json_replacer/docx_replacer.py
docx_json_replacer/formatting_handler.py
docx_json_replacer/table_handler.py
docx_json_replacer/utility/__init__.py
docx_json_replacer/utility/html_parse.py
docx_json_replacer/utility/html_parse_simple.py
docx_json_replacer-0.7.3.dist-info/licenses/LICENSE
docx_json_replacer-0.7.3.dist-info/METADATA
docx_json_replacer-0.7.3.dist-info/WHEEL
docx_json_replacer-0.7.3.dist-info/entry_points.txt
docx_json_replacer-0.7.3.dist-info/top_level.txt
docx_json_replacer-0.7.3.dist-info/RECORD
