Metadata-Version: 2.4
Name: docx-json-replacer
Version: 0.7.3
Summary: Replace template placeholders in DOCX files with JSON data, supports tables with HTML formatting and cell-level styling
Home-page: https://github.com/liuspatt/docx-json-replacer
Author: liuspatt
Author-email: liuspatt <liuspatt@example.com>
License: MIT
Project-URL: Homepage, https://github.com/liuspatt/docx-json-replacer
Project-URL: Repository, https://github.com/liuspatt/docx-json-replacer
Project-URL: Issues, https://github.com/liuspatt/docx-json-replacer/issues
Project-URL: Changelog, https://github.com/liuspatt/docx-json-replacer/blob/main/CHANGELOG.md
Project-URL: Documentation, https://github.com/liuspatt/docx-json-replacer#readme
Keywords: docx,json,template,replace,table,html,formatting,cell-styling,document-generation,office,word,automation
Classifier: Development Status :: 4 - Beta
Classifier: Intended Audience :: Developers
Classifier: Intended Audience :: Information Technology
Classifier: Intended Audience :: End Users/Desktop
Classifier: License :: OSI Approved :: MIT License
Classifier: Operating System :: OS Independent
Classifier: Programming Language :: Python :: 3
Classifier: Programming Language :: Python :: 3.7
Classifier: Programming Language :: Python :: 3.8
Classifier: Programming Language :: Python :: 3.9
Classifier: Programming Language :: Python :: 3.10
Classifier: Programming Language :: Python :: 3.11
Classifier: Programming Language :: Python :: 3.12
Classifier: Programming Language :: Python :: 3.13
Classifier: Topic :: Office/Business
Classifier: Topic :: Software Development :: Libraries :: Python Modules
Classifier: Topic :: Text Processing
Classifier: Topic :: Text Processing :: Markup :: HTML
Classifier: Typing :: Typed
Requires-Python: >=3.7
License-File: LICENSE
Requires-Dist: python-docx>=0.8.11
Requires-Dist: docxcompose>=1.3.0
Dynamic: author
Dynamic: home-page
Dynamic: license-file
Dynamic: requires-python
